etheno/__init__.py
etheno/__main__.py
etheno/ascii_escapes.py
etheno/client.py
etheno/contracts.py
etheno/differentials.py
etheno/etheno.py
etheno/ganache.py
etheno/genesis.py
etheno/geth.py
etheno/jsonrpc.py
etheno/jsonrpcclient.py
etheno/keyfile.py
etheno/logger.py
etheno/parity.py
etheno/signals.py
etheno/synchronization.py
etheno/threadwrapper.py
etheno/truffle.py
etheno/utils.py
etheno-0.3.2.dist-info/LICENSE
etheno-0.3.2.dist-info/METADATA
etheno-0.3.2.dist-info/WHEEL
etheno-0.3.2.dist-info/entry_points.txt
etheno-0.3.2.dist-info/top_level.txt
etheno-0.3.2.dist-info/RECORD
