Metadata-Version: 2.1
Name: etheno
Version: 0.3.2
Summary: Etheno is a JSON RPC multiplexer, differential fuzzer, and test framework integration tool.
Home-page: https://github.com/trailofbits/etheno
Author: Trail of Bits
Classifier: Development Status :: 4 - Beta
Classifier: Environment :: Console
Classifier: Intended Audience :: Developers
Classifier: License :: OSI Approved :: GNU Affero General Public License v3
Classifier: Topic :: Security
Classifier: Topic :: Software Development :: Testing
Requires-Python: >=3.7
License-File: LICENSE
Requires-Dist: ptyprocess
Requires-Dist: pysha3 (>=1.0.2)
Requires-Dist: flask
Requires-Dist: web3 (>=3.16.4)
Requires-Dist: eth-hash (<0.4.0,>=0.3.1)
Requires-Dist: eth-utils (==1.10.0)
Requires-Dist: eth-rlp (<0.3.0)
Requires-Dist: setuptools
